xtu/edu/captcha/CharMap.py
xtu/edu/captcha/__init__.py
xtu/edu/captcha/api.py
xtu_edu_captcha_solver-0.0.2.dist-info/METADATA
xtu_edu_captcha_solver-0.0.2.dist-info/WHEEL
xtu_edu_captcha_solver-0.0.2.dist-info/top_level.txt
xtu_edu_captcha_solver-0.0.2.dist-info/RECORD
