Metadata-Version: 2.2
Name: xtu-edu-captcha-solver
Version: 0.0.2
Summary: 湘潭大学教务系统验证码识别
Author-email: YangRucheng <admin@yangrucheng.top>
License: MIT
Project-URL: homepage, https://github.com/xtu-org/xtu-edu-captcha
Project-URL: repository, https://github.com/xtu-org/xtu-edu-captcha
Requires-Python: >=3.10
Requires-Dist: httpx>0.28.0
Requires-Dist: opencv-python>=4.10.0
